jiragen/main.py
jiragen/cli/__init__.py
jiragen/cli/add.py
jiragen/cli/clean.py
jiragen/cli/fetch.py
jiragen/cli/generate.py
jiragen/cli/init.py
jiragen/cli/kill.py
jiragen/cli/nvim.py
jiragen/cli/restart.py
jiragen/cli/rm.py
jiragen/cli/status.py
jiragen/cli/upload.py
jiragen/core/__init__.py
jiragen/core/base.py
jiragen/core/client.py
jiragen/core/config.py
jiragen/core/generator.py
jiragen/core/metadata.py
jiragen/services/jira.py
jiragen/services/vector_store.py
jiragen/templates/default.md
jiragen/utils/data.py
jiragen/utils/logger.py
jiragen/utils/misc.py
jiragen-0.5.0.dist-info/METADATA
jiragen-0.5.0.dist-info/WHEEL
jiragen-0.5.0.dist-info/entry_points.txt
jiragen-0.5.0.dist-info/licenses/LICENSE
jiragen-0.5.0.dist-info/RECORD
