Metadata-Version: 2.4
Name: jiragen
Version: 0.5.0
Summary: RAG-based JIRA ticket generator using vector similarity search
Project-URL: Homepage, https://github.com/Abdellah-Laassairi/jiragen
Project-URL: Bug Tracker, https://github.com/Abdellah-Laassairi/jiragen/issues
Author-email: Abdellah Laassairi <laassairi.abdellah@gmail.com>
License-File: LICENSE
Classifier: Development Status :: 3 - Alpha
Classifier: Intended Audience :: Developers
Classifier: Operating System :: OS Independent
Classifier: Programming Language :: Python :: 3
Classifier: Programming Language :: Python :: 3.10
Classifier: Programming Language :: Python :: 3.11
Classifier: Topic :: Software Development :: Documentation
Classifier: Topic :: Software Development :: Libraries :: Python Modules
Requires-Python: >=3.10
Requires-Dist: atlassian-python-api==3.41.16
Requires-Dist: charset-normalizer>=3.0.0
Requires-Dist: chromadb
Requires-Dist: jira==3.5.1
Requires-Dist: litellm==1.55.12
Requires-Dist: loguru==0.7.2
Requires-Dist: markdown==3.4.3
Requires-Dist: pathspec==0.12.1
Requires-Dist: pydantic>=2.0.0
Requires-Dist: requests>=2.31.0
Requires-Dist: rich>=13.0.0
Requires-Dist: sentence-transformers
Requires-Dist: typer>=0.9.0
Requires-Dist: urllib3>=2.0.0
